topsis/__init__.py
topsis/topsis.py
Topsis_Sailish_102003768-1.0.0.dist-info/LICENCE.txt
Topsis_Sailish_102003768-1.0.0.dist-info/METADATA
Topsis_Sailish_102003768-1.0.0.dist-info/WHEEL
Topsis_Sailish_102003768-1.0.0.dist-info/entry_points.txt
Topsis_Sailish_102003768-1.0.0.dist-info/top_level.txt
Topsis_Sailish_102003768-1.0.0.dist-info/RECORD
