Metadata-Version: 2.1
Name: Topsis-Sailish-102003768
Version: 1.0.0
Summary: A TOPSIS calculator
Home-page: 
Author: Sailish Makkar
Author-email: smakkar_be20@thapar.edu
License: MIT
Keywords: TOPSIS
Classifier: Programming Language :: Python :: 3
Classifier: License :: OSI Approved :: MIT License
Classifier: Operating System :: OS Independent
License-File: LICENCE.txt
